elfhex/__init__.py
elfhex/__main__.py
elfhex/elf.py
elfhex/elfhex.lark
elfhex/file_loader.py
elfhex/preprocessor.py
elfhex/program.py
elfhex/transformer.py
elfhex/util.py
elfhex/extensions/README.md
elfhex/extensions/__init__.py
elfhex/extensions/x86/__init__.py
elfhex/extensions/x86/args.py
elfhex/extensions/x86/x86.lark
elfhex-0.0.8.dist-info/LICENSE
elfhex-0.0.8.dist-info/METADATA
elfhex-0.0.8.dist-info/WHEEL
elfhex-0.0.8.dist-info/entry_points.txt
elfhex-0.0.8.dist-info/pbr.json
elfhex-0.0.8.dist-info/top_level.txt
elfhex-0.0.8.dist-info/RECORD
