Metadata-Version: 2.1
Name: elfhex
Version: 0.0.8
Summary: A small "assembler" for ELF executables
Home-page: https://github.com/Synook/elfhex
Author: Google LLC
License: Apache-2
Platform: UNKNOWN
Classifier: Programming Language :: Python :: 3.6
Classifier: Programming Language :: Python :: 3.7
Classifier: License :: OSI Approved :: Apache Software License
Classifier: Operating System :: OS Independent
Requires-Python: >=3.6
Requires-Dist: lark-parser (>=0.7.4)
